MANIFEST.in
README.rst
setup.py
jk_commentjson/__init__.py
jk_commentjson/commentjson.py
jk_commentjson.egg-info/PKG-INFO
jk_commentjson.egg-info/SOURCES.txt
jk_commentjson.egg-info/dependency_links.txt
jk_commentjson.egg-info/not-zip-safe
jk_commentjson.egg-info/top_level.txt