Metadata-Version: 1.1
Name: jk-commentjson
Version: 0.2017.10.7
Summary: This is a JSON parsing module that can get along with comments in JSON files.
Home-page: https://github.com/jkpubsrc/python-module-jk-commentjson
Author: Jürgen Knauth
Author-email: pubsrc@binary-overflow.de
License: Apache 2.0
Download-URL: https://github.com/jkpubsrc/python-module-jk-commentjson/tarball/0.2017.10.7
Keywords: json
Platform: UNKNOWN
Classifier: Development Status :: 4 - Beta
Classifier: Programming Language :: Python :: 3.5
Classifier: License :: OSI Approved :: Apache Software License
